{
  "entrypoints": [
    "main"
  ],
  "origins": {
    "@theme/NotFound": [
      1,
      2,
      3,
      5,
      7,
      9,
      11,
      0
    ],
    "docsearch.js": [
      1,
      2,
      3,
      5,
      7,
      9,
      11,
      0
    ],
    "common": [
      0,
      2,
      3,
      1
    ],
    "/mnt/c/Users/endij/Desktop/Linux/endiliey.github.io/components/BlogPage": [
      0,
      1,
      2
    ],
    "/mnt/c/Users/endij/Desktop/Linux/endiliey.github.io/components/BlogPost": [
      0,
      1,
      3
    ],
    "main": [
      12,
      4
    ],
    "/mnt/c/Users/endij/Desktop/Linux/endiliey.github.io/blog/2019-04-29-hello-world.md?truncated=true": [
      0,
      5
    ],
    "/mnt/c/Users/endij/Desktop/Linux/endiliey.github.io/.docusaurus/docusaurus-plugin-content-blog/2018-08-11-introducing-idne-295.json": [
      6
    ],
    "/mnt/c/Users/endij/Desktop/Linux/endiliey.github.io/blog/2018-08-11-introducing-idne.md": [
      0,
      7
    ],
    "/mnt/c/Users/endij/Desktop/Linux/endiliey.github.io/.docusaurus/docusaurus-plugin-content-blog/2019-04-29-hello-world-1ab.json": [
      8
    ],
    "/mnt/c/Users/endij/Desktop/Linux/endiliey.github.io/blog/2019-04-29-hello-world.md": [
      0,
      9
    ],
    "/mnt/c/Users/endij/Desktop/Linux/endiliey.github.io/.docusaurus/docusaurus-plugin-content-blog/index.json": [
      10
    ],
    "/mnt/c/Users/endij/Desktop/Linux/endiliey.github.io/blog/2018-08-11-introducing-idne.md?truncated=true": [
      0,
      11
    ],
    "runtime~main": [
      4,
      12
    ]
  },
  "assets": {
    "0": {
      "css": [
        {
          "file": "vendors.07505a71c785db753742.css",
          "hash": "07505a71c785db753742",
          "publicPath": "/vendors.07505a71c785db753742.css"
        }
      ],
      "js": [
        {
          "file": "vendors.07505a71c785db753742.js",
          "hash": "07505a71c785db753742",
          "publicPath": "/vendors.07505a71c785db753742.js"
        }
      ]
    },
    "1": {
      "css": [
        {
          "file": "common.37134455f3af010ead43.css",
          "hash": "37134455f3af010ead43",
          "publicPath": "/common.37134455f3af010ead43.css"
        }
      ],
      "js": [
        {
          "file": "common.37134455f3af010ead43.js",
          "hash": "37134455f3af010ead43",
          "publicPath": "/common.37134455f3af010ead43.js"
        }
      ]
    },
    "2": {
      "js": [
        {
          "file": "component---mnt-c-users-endij-desktop-linux-endiliey-github-io-components-blog-page-8ad.c758eaf87b106629677e.js",
          "hash": "c758eaf87b106629677e",
          "publicPath": "/component---mnt-c-users-endij-desktop-linux-endiliey-github-io-components-blog-page-8ad.c758eaf87b106629677e.js"
        }
      ]
    },
    "3": {
      "js": [
        {
          "file": "component---mnt-c-users-endij-desktop-linux-endiliey-github-io-components-blog-post-a61.e36bd2e15823eb40aa00.js",
          "hash": "e36bd2e15823eb40aa00",
          "publicPath": "/component---mnt-c-users-endij-desktop-linux-endiliey-github-io-components-blog-post-a61.e36bd2e15823eb40aa00.js"
        }
      ]
    },
    "4": {
      "css": [
        {
          "file": "main.cee8105c4464d11e6f3a.css",
          "hash": "cee8105c4464d11e6f3a",
          "publicPath": "/main.cee8105c4464d11e6f3a.css"
        }
      ],
      "js": [
        {
          "file": "main.cee8105c4464d11e6f3a.js",
          "hash": "cee8105c4464d11e6f3a",
          "publicPath": "/main.cee8105c4464d11e6f3a.js"
        }
      ]
    },
    "5": {
      "js": [
        {
          "file": "module---2-d-2-c46.ed7e0d7b242c52cf430a.js",
          "hash": "ed7e0d7b242c52cf430a",
          "publicPath": "/module---2-d-2-c46.ed7e0d7b242c52cf430a.js"
        }
      ]
    },
    "6": {
      "js": [
        {
          "file": "module---2018-08-11-introducing-idnea-16-1f9.d6723ae3923e5d087609.js",
          "hash": "d6723ae3923e5d087609",
          "publicPath": "/module---2018-08-11-introducing-idnea-16-1f9.d6723ae3923e5d087609.js"
        }
      ]
    },
    "7": {
      "js": [
        {
          "file": "module---2018-08-11-introducing-idnebc-9-83b.2d0c5bc81c36bda3af33.js",
          "hash": "2d0c5bc81c36bda3af33",
          "publicPath": "/module---2018-08-11-introducing-idnebc-9-83b.2d0c5bc81c36bda3af33.js"
        }
      ]
    },
    "8": {
      "js": [
        {
          "file": "module---2019-04-29-hello-world-49-f-6cf.f5ce03df709ef3920998.js",
          "hash": "f5ce03df709ef3920998",
          "publicPath": "/module---2019-04-29-hello-world-49-f-6cf.f5ce03df709ef3920998.js"
        }
      ]
    },
    "9": {
      "js": [
        {
          "file": "module---2019-04-29-hello-worldff-1-ec0.8619fe480542d54521ae.js",
          "hash": "8619fe480542d54521ae",
          "publicPath": "/module---2019-04-29-hello-worldff-1-ec0.8619fe480542d54521ae.js"
        }
      ]
    },
    "10": {
      "js": [
        {
          "file": "module---5-ea-c9c.4ea68c969a0dc97e5876.js",
          "hash": "4ea68c969a0dc97e5876",
          "publicPath": "/module---5-ea-c9c.4ea68c969a0dc97e5876.js"
        }
      ]
    },
    "11": {
      "js": [
        {
          "file": "module---f-7-d-1f4.e5a3c1aa0e6bf8b9d5fa.js",
          "hash": "e5a3c1aa0e6bf8b9d5fa",
          "publicPath": "/module---f-7-d-1f4.e5a3c1aa0e6bf8b9d5fa.js"
        }
      ]
    },
    "12": {
      "js": [
        {
          "file": "runtime~main.4938d28dfbb606f526c3.js",
          "hash": "4938d28dfbb606f526c3",
          "publicPath": "/runtime~main.4938d28dfbb606f526c3.js"
        }
      ]
    }
  }
}